setup.py
lib/PyFizzBuzz.egg-info/PKG-INFO
lib/PyFizzBuzz.egg-info/SOURCES.txt
lib/PyFizzBuzz.egg-info/dependency_links.txt
lib/PyFizzBuzz.egg-info/top_level.txt
lib/bin/bizzbuzz
lib/bin/fizzbuzz
lib/fizzbuzz/__init__.py
lib/fizzbuzz/bizzbuzz.py
lib/fizzbuzz/fizzbuzz.py
lib/fizzbuzz/fizzbuzz_abs.py