Metadata-Version: 1.1
Name: PyFizzBuzz
Version: 0.0.2
Summary: FizzBuzz cli tool
Home-page: https://github.com/futoase/fizzbuzz
Author: Keiji Matsuzaki
Author-email: futoase@gmail.com
License: MIT License
Platform: UNKNOWN
Classifier: Programming Language :: Python :: 3.2
Classifier: Programming Language :: Python :: 3.3
Classifier: License :: OSI Approved :: MIT License
